{"title":"玄武门","blocks":[{"type":"p","text":"“去洛阳吧，把天策府的将领留下。”大哥拨弄着茶盏，没有抬头。"},{"type":"p","text":"“洛阳太近了。”二弟笑了笑，声音里听不出喜怒，“就算我愿意去，长孙无忌他们不敢信，魏徵他们更睡不着。”"},{"type":"p","text":"大哥手里的动作停了：“难道真要在这长安城里，溅你我兄弟一身血，让外人看笑话吗？”"},{"type":"p","text":"“不是我想溅血，是底下的刀已经拔出来了，谁也收不回去。”二弟看向门外，目光冷硬，“大哥，东宫和天策府，只能活一个。这是天家的规矩。”"},{"type":"p","text":"大哥抬起眼，静静地看着这个从小跟在自己身后、如今却百战满身杀气的弟弟。良久，他冷笑了一声：\n“我若是退了，你能留我性命吗？”"},{"type":"p","text":"“大哥信得过我，天策府的人信不过。”二弟平静地看着他，“就像大哥若是赢了，东宫的属官，也绝不会让我活到明天。”"},{"type":"p","text":"大哥站起身，理了理衣袍，恢复了储君的威仪。他看着二弟，眼中最后一丝属于兄弟的温度也彻底褪去了。"},{"type":"p","text":"“我是太子。大唐的宗祧，只能由我来继。既然话已至此——明日早朝，太极宫见吧。”"},{"type":"p","text":"二弟深深作了一揖，行的是无可挑剔的君臣之礼：“臣弟，告退。”"},{"type":"p","text":"那天清晨，玄武门前的晨雾异常浓重。太极宫的钟声尚未敲响，暗藏的刀锋已将大唐的命运割裂。没有悲壮的牺牲，也没有体面的告别，只有你死我活的兽性搏杀。"},{"type":"p","text":"“庚申，世民帅长孙无忌等入，伏兵于玄武门。\n建成、元吉至临湖殿，觉变，即跋马东归宫府。\n世民从而呼之，元吉张弓射世民，再三不彀，世民射建成，杀之。\n尉迟敬德将七十骑继至，左右射元吉坠马。世民马逸入林下，为木枝所絓，坠不能起。元吉遽至，夺弓将扼之，敬德跃马叱之。元吉步欲趣武德殿，敬德追射，杀之。”"},{"type":"p","text":"——《资治通鉴》卷一九一"}]}